fields_history/__init__.py
fields_history/base.py
fields_history/models.py
fields_history/postgres/__init__.py
fields_history/postgres/apps.py
fields_history/postgres/managers.py
fields_history/postgres/migrations/0001_initial.py
fields_history/postgres/migrations/0002_alter_fieldshistory_history.py
fields_history/postgres/migrations/__init__.py
fields_history/postgres/models.py
fields_history/trackers.py
django_fields_history-0.1.7.dist-info/METADATA
django_fields_history-0.1.7.dist-info/WHEEL
django_fields_history-0.1.7.dist-info/RECORD
